{
    "Name": "Coffee Cake",
    "Description": "There is enough caffeine to keep you up for a week!",
    "Category": "Cooking",
    "Edibility": 35,
    "EdibleIsDrink": false,
    "EdibleBuffs":
    {
        "Farming": 0,
        "Fishing": 0,
        "Mining": 0,
        "Luck": 0,
        "Foraging": 0,
        "MaxStamina": 0,
        "MagnetRadius": 0,
        "Speed": 1,
        "Defense": 0,
        "Attack": 0,
        "Duration": 10000,
    },
    "Price": 1000,
    "IsColored": false,
    "CanPurchase": false,
    "Recipe":
    {
        "ResultCount": 1,
        "Ingredients": [
        {
            "Object": 253, //triple shot espresso
            "Count": 3,
        },
        {
            "Object": 246, //wheat
            "Count": 1,
        },
        ],
    "IsDefault": true,
    },
}