{
  "winter_18": "900 AnimalShop 7 5 0 \"Strings\\schedules\\Jas:winter_18.000\"/1030 Hospital 12 14 0/1330 Hospital 4 6 1 \"Strings\\schedules\\Jas:winter_18.001\"/1600 AnimalShop 17 5 3 jas_read/2000 AnimalShop 1 7 3 jas_sleep",
  "Mon": "610 School 7 25 0/1200 School 42 20 2/1300 School 43 20 2/1330 School 36 22 1/1500 School 38 9 2 jas_jumprope/1650 School 7 25 0/1830 AnimalShop 1 7 3 jas_sleep",
  "Tue": "610 School 7 25 0/1200 School 42 20 2/1300 School 43 20 2/1330 School 36 22 1/1500 School 36 33 0/1650 School 7 25 0/1830 AnimalShop 1 7 3 jas_sleep",
  "Wed": "GOTO Mon",
  "Thu": "GOTO Tue",
  "Fri": "GOTO Mon",
  "Sat": "1000 Town 31 89 1/1200 Town 24 12 jas_jumprope/1700 Town 28 90 1/2000 AnimalShop 1 7 3 jas_sleep",
  "Sun": "GOTO Sat"
}