{
  "npcList": [
    {
      "npc": "Default",
      "gifts": [
        {
          "item": "60",
          "quality": 0,
          "seasons": [
            "Spring",
            "Summer",
            "Fall",
            "Winter"
          ],
          "requireHeart": 0,
          "stackMin": 1,
          "stackMax": 1
        },
        {
          "item": "62",
          "quality": 0,
          "seasons": [
            "Spring",
            "Summer",
            "Fall",
            "Winter"
          ],
          "requireHeart": 0,
          "stackMin": 1,
          "stackMax": 1
        },
        {
          "item": "64",
          "quality": 0,
          "seasons": [
            "Spring",
            "Summer",
            "Fall",
            "Winter"
          ],
          "requireHeart": 0,
          "stackMin": 1,
          "stackMax": 1
        },
        {
          "item": "70",
          "quality": 0,
          "seasons": [
            "Spring",
            "Summer",
            "Fall",
            "Winter"
          ],
          "requireHeart": 0,
          "stackMin": 1,
          "stackMax": 1
        },
        {
          "item": "72",
          "quality": 0,
          "seasons": [
            "Spring",
            "Summer",
            "Fall",
            "Winter"
          ],
          "requireHeart": 8,
          "stackMin": 1,
          "stackMax": 1
        }
      ]
    },
    {
      "npc": "Alex",
      "gifts": [
        {
          "item": "174",
          "quality": 2,
          "seasons": [
            "Spring",
            "Summer",
            "Fall",
            "Winter"
          ],
          "requireHeart": 0,
          "stackMin": 2,
          "stackMax": 2
        },
        {
          "item": "233",
          "quality": 4,
          "seasons": [
            "Spring",
            "Summer",
            "Fall",
            "Winter"
          ],
          "requireHeart": 0,
          "stackMin": 1,
          "stackMax": 1
        },
        {
          "item": "221",
          "quality": 0,
          "seasons": [
            "Spring",
            "Summer",
            "Fall",
            "Winter"
          ],
          "requireHeart": 0,
          "stackMin": 1,
          "stackMax": 1
        },
        {
          "item": "239",
          "quality": 1,
          "seasons": [
            "Spring",
            "Summer",
            "Fall",
            "Winter"
          ],
          "requireHeart": 0,
          "stackMin": 1,
          "stackMax": 1
        },
        {
          "item": "205",
          "quality": 0,
          "seasons": [
            "Spring",
            "Summer",
            "Fall",
            "Winter"
          ],
          "requireHeart": 0,
          "stackMin": 1,
          "stackMax": 1
        }
      ]
    },
    {
      "npc": "Elliott",
      "gifts": [
        {
          "item": "459",
          "quality": 0,
          "seasons": [
            "Spring",
            "Summer",
            "Fall",
            "Winter"
          ],
          "requireHeart": 0,
          "stackMin": 1,
          "stackMax": 1
        },
        {
          "item": "392",
          "quality": 4,
          "seasons": [
            "Spring",
            "Summer",
            "Fall",
            "Winter"
          ],
          "requireHeart": 0,
          "stackMin": 1,
          "stackMax": 1
        },
        {
          "item": "196",
          "quality": 4,
          "seasons": [
            "Spring",
            "Summer",
            "Fall",
            "Winter"
          ],
          "requireHeart": 0,
          "stackMin": 1,
          "stackMax": 1
        },
        {
          "item": "348",
          "quality": 0,
          "seasons": [
            "Spring",
            "Summer",
            "Fall",
            "Winter"
          ],
          "requireHeart": 0,
          "stackMin": 1,
          "stackMax": 1
        }
      ]
    },
    {
      "npc": "Harvey",
      "gifts": [
        {
          "item": "349",
          "quality": 0,
          "seasons": [
            "Spring",
            "Summer",
            "Fall",
            "Winter"
          ],
          "requireHeart": 0,
          "stackMin": 1,
          "stackMax": 1
        },
        {
          "item": "351",
          "quality": 0,
          "seasons": [
            "Spring",
            "Summer",
            "Fall",
            "Winter"
          ],
          "requireHeart": 0,
          "stackMin": 1,
          "stackMax": 1
        },
        {
          "item": "243",
          "quality": 0,
          "seasons": [
            "Spring",
            "Summer",
            "Fall",
            "Winter"
          ],
          "requireHeart": 0,
          "stackMin": 1,
          "stackMax": 1
        },
        {
          "item": "197",
          "quality": 0,
          "seasons": [
            "Spring",
            "Summer",
            "Fall",
            "Winter"
          ],
          "requireHeart": 0,
          "stackMin": 1,
          "stackMax": 1
        }
      ]
    },
    {
      "npc": "Sam",
      "gifts": [
        {
          "item": "167",
          "quality": 0,
          "seasons": [
            "Spring",
            "Summer",
            "Fall",
            "Winter"
          ],
          "requireHeart": 0,
          "stackMin": 5,
          "stackMax": 5
        },
        {
          "item": "724",
          "quality": 0,
          "seasons": [
            "Spring",
            "Summer",
            "Fall",
            "Winter"
          ],
          "requireHeart": 0,
          "stackMin": 1,
          "stackMax": 1
        },
        {
          "item": "60",
          "quality": 0,
          "seasons": [
            "Spring",
            "Summer",
            "Fall",
            "Winter"
          ],
          "requireHeart": 0,
          "stackMin": 1,
          "stackMax": 1
        },
        {
          "item": "903",
          "quality": 0,
          "seasons": [
            "Spring",
            "Summer",
            "Fall",
            "Winter"
          ],
          "requireHeart": 0,
          "stackMin": 1,
          "stackMax": 1
        },
        {
          "item": "211",
          "quality": 4,
          "seasons": [
            "Spring",
            "Summer",
            "Fall",
            "Winter"
          ],
          "requireHeart": 0,
          "stackMin": 1,
          "stackMax": 1
        }
      ]
    },
    {
      "npc": "Sebastian",
      "gifts": [
        {
          "item": "66",
          "quality": 0,
          "seasons": [
            "Spring",
            "Summer",
            "Fall",
            "Winter"
          ],
          "requireHeart": 0,
          "stackMin": 2,
          "stackMax": 2
        },
        {
          "item": "611",
          "quality": 0,
          "seasons": [
            "Spring",
            "Summer",
            "Fall",
            "Winter"
          ],
          "requireHeart": 0,
          "stackMin": 1,
          "stackMax": 1
        },
        {
          "item": "244",
          "quality": 4,
          "seasons": [
            "Spring",
            "Summer",
            "Fall",
            "Winter"
          ],
          "requireHeart": 0,
          "stackMin": 1,
          "stackMax": 1
        },
        {
          "item": "731",
          "quality": 0,
          "seasons": [
            "Spring",
            "Summer",
            "Fall",
            "Winter"
          ],
          "requireHeart": 0,
          "stackMin": 1,
          "stackMax": 1
        }
      ]
    },
    {
      "npc": "Shane",
      "gifts": [
        {
          "item": "182",
          "quality": 2,
          "seasons": [
            "Spring",
            "Summer",
            "Fall",
            "Winter"
          ],
          "requireHeart": 0,
          "stackMin": 2,
          "stackMax": 2
        },
        {
          "item": "303",
          "quality": 0,
          "seasons": [
            "Spring",
            "Summer",
            "Fall",
            "Winter"
          ],
          "requireHeart": 0,
          "stackMin": 1,
          "stackMax": 1
        },
        {
          "item": "64",
          "quality": 0,
          "seasons": [
            "Spring",
            "Summer",
            "Fall",
            "Winter"
          ],
          "requireHeart": 0,
          "stackMin": 1,
          "stackMax": 1
        },
        {
          "item": "604",
          "quality": 0,
          "seasons": [
            "Spring",
            "Summer",
            "Fall",
            "Winter"
          ],
          "requireHeart": 0,
          "stackMin": 1,
          "stackMax": 1
        },
        {
          "item": "240",
          "quality": 1,
          "seasons": [
            "Spring",
            "Summer",
            "Fall",
            "Winter"
          ],
          "requireHeart": 0,
          "stackMin": 1,
          "stackMax": 1
        }
      ]
    },
    {
      "npc": "Abigail",
      "gifts": [
        {
          "item": "202",
          "quality": 1,
          "seasons": [
            "Spring",
            "Summer",
            "Fall",
            "Winter"
          ],
          "requireHeart": 0,
          "stackMin": 1,
          "stackMax": 1
        },
        {
          "item": "236",
          "quality": 0,
          "seasons": [
            "Spring",
            "Summer",
            "Fall",
            "Winter"
          ],
          "requireHeart": 0,
          "stackMin": 1,
          "stackMax": 1
        },
        {
          "item": "907",
          "quality": 0,
          "seasons": [
            "Spring",
            "Summer",
            "Fall",
            "Winter"
          ],
          "requireHeart": 0,
          "stackMin": 1,
          "stackMax": 1
        },
        {
          "item": "84",
          "quality": 0,
          "seasons": [
            "Spring",
            "Summer",
            "Fall",
            "Winter"
          ],
          "requireHeart": 0,
          "stackMin": 3,
          "stackMax": 3
        }
      ]
    },
    {
      "npc": "Emily",
      "gifts": [
        {
          "item": "206",
          "quality": 0,
          "seasons": [
            "Spring",
            "Summer",
            "Fall",
            "Winter"
          ],
          "requireHeart": 0,
          "stackMin": 1,
          "stackMax": 1
        },
        {
          "item": "88",
          "quality": 4,
          "seasons": [
            "Spring",
            "Summer",
            "Fall",
            "Winter"
          ],
          "requireHeart": 0,
          "stackMin": 1,
          "stackMax": 1
        },
        {
          "item": "90",
          "quality": 2,
          "seasons": [
            "Spring",
            "Summer",
            "Fall",
            "Winter"
          ],
          "requireHeart": 0,
          "stackMin": 2,
          "stackMax": 2
        },
        {
          "item": "215",
          "quality": 0,
          "seasons": [
            "Spring",
            "Summer",
            "Fall",
            "Winter"
          ],
          "requireHeart": 0,
          "stackMin": 1,
          "stackMax": 1
        }
      ]
    },
    {
      "npc": "Haley",
      "gifts": [
        {
          "item": "62",
          "quality": 0,
          "seasons": [
            "Spring",
            "Summer",
            "Fall",
            "Winter"
          ],
          "requireHeart": 0,
          "stackMin": 1,
          "stackMax": 1
        },
        {
          "item": "212",
          "quality": 0,
          "seasons": [
            "Spring",
            "Summer",
            "Fall",
            "Winter"
          ],
          "requireHeart": 0,
          "stackMin": 1,
          "stackMax": 1
        },
        {
          "item": "428",
          "quality": 0,
          "seasons": [
            "Spring",
            "Summer",
            "Fall",
            "Winter"
          ],
          "requireHeart": 0,
          "stackMin": 1,
          "stackMax": 1
        },
        {
          "item": "68",
          "quality": 0,
          "seasons": [
            "Spring",
            "Summer",
            "Fall",
            "Winter"
          ],
          "requireHeart": 0,
          "stackMin": 2,
          "stackMax": 2
        }
      ]
    },
    {
      "npc": "Leah",
      "gifts": [
        {
          "item": "444",
          "quality": 0,
          "seasons": [
            "Spring",
            "Summer",
            "Fall",
            "Winter"
          ],
          "requireHeart": 0,
          "stackMin": 1,
          "stackMax": 1
        },
        {
          "item": "218",
          "quality": 0,
          "seasons": [
            "Spring",
            "Summer",
            "Fall",
            "Winter"
          ],
          "requireHeart": 0,
          "stackMin": 1,
          "stackMax": 1
        },
        {
          "item": "613",
          "quality": 4,
          "seasons": [
            "Spring",
            "Summer",
            "Fall",
            "Winter"
          ],
          "requireHeart": 0,
          "stackMin": 1,
          "stackMax": 1
        },
        {
          "item": "634",
          "quality": 4,
          "seasons": [
            "Spring",
            "Summer",
            "Fall",
            "Winter"
          ],
          "requireHeart": 0,
          "stackMin": 2,
          "stackMax": 2
        },
        {
          "item": "638",
          "quality": 4,
          "seasons": [
            "Spring",
            "Summer",
            "Fall",
            "Winter"
          ],
          "requireHeart": 0,
          "stackMin": 1,
          "stackMax": 1
        },
        {
          "item": "636",
          "quality": 4,
          "seasons": [
            "Spring",
            "Summer",
            "Fall",
            "Winter"
          ],
          "requireHeart": 0,
          "stackMin": 1,
          "stackMax": 1
        },
        {
          "item": "637",
          "quality": 4,
          "seasons": [
            "Spring",
            "Summer",
            "Fall",
            "Winter"
          ],
          "requireHeart": 0,
          "stackMin": 1,
          "stackMax": 1
        },
        {
          "item": "635",
          "quality": 4,
          "seasons": [
            "Spring",
            "Summer",
            "Fall",
            "Winter"
          ],
          "requireHeart": 0,
          "stackMin": 1,
          "stackMax": 1
        },
        {
          "item": "18",
          "quality": 4,
          "seasons": [
            "Spring",
            "Summer",
            "Fall",
            "Winter"
          ],
          "requireHeart": 0,
          "stackMin": 3,
          "stackMax": 4
        }
      ]
    },
    {
      "npc": "Maru",
      "gifts": [
        {
          "item": "395",
          "quality": 0,
          "seasons": [
            "Spring",
            "Summer",
            "Fall",
            "Winter"
          ],
          "requireHeart": 0,
          "stackMin": 2,
          "stackMax": 2
        },
        {
          "item": "237",
          "quality": 0,
          "seasons": [
            "Spring",
            "Summer",
            "Fall",
            "Winter"
          ],
          "requireHeart": 0,
          "stackMin": 1,
          "stackMax": 1
        },
        {
          "item": "232",
          "quality": 0,
          "seasons": [
            "Spring",
            "Summer",
            "Fall",
            "Winter"
          ],
          "requireHeart": 0,
          "stackMin": 1,
          "stackMax": 1
        },
        {
          "item": "224",
          "quality": 0,
          "seasons": [
            "Spring",
            "Summer",
            "Fall",
            "Winter"
          ],
          "requireHeart": 0,
          "stackMin": 1,
          "stackMax": 1
        }
      ]
    },
    {
      "npc": "Penny",
      "gifts": [
        {
          "item": "199",
          "quality": 4,
          "seasons": [
            "Spring",
            "Summer",
            "Fall",
            "Winter"
          ],
          "requireHeart": 0,
          "stackMin": 1,
          "stackMax": 1
        },
        {
          "item": "221",
          "quality": 0,
          "seasons": [
            "Spring",
            "Summer",
            "Fall",
            "Winter"
          ],
          "requireHeart": 0,
          "stackMin": 1,
          "stackMax": 1
        },
        {
          "item": "612",
          "quality": 2,
          "seasons": [
            "Spring",
            "Summer",
            "Fall",
            "Winter"
          ],
          "requireHeart": 0,
          "stackMin": 1,
          "stackMax": 1
        },
        {
          "item": "731",
          "quality": 0,
          "seasons": [
            "Spring",
            "Summer",
            "Fall",
            "Winter"
          ],
          "requireHeart": 0,
          "stackMin": 1,
          "stackMax": 1
        }
      ]
    },
    {
      "npc": "Caroline",
      "gifts": [
        {
          "item": "202",
          "quality": 1,
          "seasons": [
            "Spring",
            "Summer",
            "Fall",
            "Winter"
          ],
          "requireHeart": 0,
          "stackMin": 1,
          "stackMax": 1
        },
        {
          "item": "815",
          "quality": 0,
          "seasons": [
            "Spring",
            "Summer",
            "Fall",
            "Winter"
          ],
          "requireHeart": 0,
          "stackMin": 3,
          "stackMax": 3
        },
        {
          "item": "220",
          "quality": 0,
          "seasons": [
            "Spring",
            "Summer",
            "Fall",
            "Winter"
          ],
          "requireHeart": 0,
          "stackMin": 1,
          "stackMax": 1
        },
        {
          "item": "200",
          "quality": 4,
          "seasons": [
            "Spring",
            "Summer",
            "Fall",
            "Winter"
          ],
          "requireHeart": 0,
          "stackMin": 1,
          "stackMax": 1
        },
        {
          "item": "190",
          "quality": 2,
          "seasons": [
            "Spring",
            "Summer",
            "Fall",
            "Winter"
          ],
          "requireHeart": 0,
          "stackMin": 1,
          "stackMax": 1
        }
      ]
    },
    {
      "npc": "Clint",
      "gifts": [
        {
          "item": "334",
          "quality": 0,
          "seasons": [
            "Spring",
            "Summer",
            "Fall",
            "Winter"
          ],
          "requireHeart": 0,
          "stackMin": 4,
          "stackMax": 4
        },
        {
          "item": "335",
          "quality": 0,
          "seasons": [
            "Spring",
            "Summer",
            "Fall",
            "Winter"
          ],
          "requireHeart": 0,
          "stackMin": 2,
          "stackMax": 2
        },
        {
          "item": "382",
          "quality": 0,
          "seasons": [
            "Spring",
            "Summer",
            "Fall",
            "Winter"
          ],
          "requireHeart": 0,
          "stackMin": 10,
          "stackMax": 10
        },
        {
          "item": "338",
          "quality": 0,
          "seasons": [
            "Spring",
            "Summer",
            "Fall",
            "Winter"
          ],
          "requireHeart": 0,
          "stackMin": 5,
          "stackMax": 5
        }
      ]
    },
    {
      "npc": "Demetrius",
      "gifts": [
        {
          "item": "222",
          "quality": 0,
          "seasons": [
            "Spring",
            "Summer",
            "Fall",
            "Winter"
          ],
          "requireHeart": 0,
          "stackMin": 1,
          "stackMax": 1
        },
        {
          "item": "575",
          "quality": 0,
          "seasons": [
            "Spring",
            "Summer",
            "Fall",
            "Winter"
          ],
          "requireHeart": 0,
          "stackMin": 1,
          "stackMax": 1
        },
        {
          "item": "426",
          "quality": 0,
          "seasons": [
            "Spring",
            "Summer",
            "Fall",
            "Winter"
          ],
          "requireHeart": 0,
          "stackMin": 1,
          "stackMax": 1
        },
        {
          "item": "394",
          "quality": 0,
          "seasons": [
            "Spring",
            "Summer",
            "Fall",
            "Winter"
          ],
          "requireHeart": 0,
          "stackMin": 1,
          "stackMax": 1
        },
        {
          "item": "392",
          "quality": 4,
          "seasons": [
            "Spring",
            "Summer",
            "Fall",
            "Winter"
          ],
          "requireHeart": 0,
          "stackMin": 1,
          "stackMax": 1
        }
      ]
    },
    {
      "npc": "Dwarf",
      "gifts": [
        {
          "item": "768",
          "quality": 0,
          "seasons": [
            "Spring",
            "Summer",
            "Fall",
            "Winter"
          ],
          "requireHeart": 0,
          "stackMin": 5,
          "stackMax": 5
        },
        {
          "item": "769",
          "quality": 0,
          "seasons": [
            "Spring",
            "Summer",
            "Fall",
            "Winter"
          ],
          "requireHeart": 0,
          "stackMin": 4,
          "stackMax": 4
        },
        {
          "item": "78",
          "quality": 4,
          "seasons": [
            "Spring",
            "Summer",
            "Fall",
            "Winter"
          ],
          "requireHeart": 0,
          "stackMin": 4,
          "stackMax": 4
        },
        {
          "item": "535",
          "quality": 0,
          "seasons": [
            "Spring",
            "Summer",
            "Fall",
            "Winter"
          ],
          "requireHeart": 0,
          "stackMin": 4,
          "stackMax": 4
        },
        {
          "item": "536",
          "quality": 0,
          "seasons": [
            "Spring",
            "Summer",
            "Fall",
            "Winter"
          ],
          "requireHeart": 0,
          "stackMin": 3,
          "stackMax": 3
        },
        {
          "item": "537",
          "quality": 0,
          "seasons": [
            "Spring",
            "Summer",
            "Fall",
            "Winter"
          ],
          "requireHeart": 0,
          "stackMin": 2,
          "stackMax": 2
        }
      ]
    },
    {
      "npc": "Example",
      "gifts": [
        {
          "item": "349",
          "quality": 0,
          "seasons": [
            "Spring",
            "Summer",
            "Fall",
            "Winter"
          ],
          "requireHeart": 0,
          "stackMin": 1,
          "stackMax": 1
        },
        {
          "item": "351",
          "quality": 0,
          "seasons": [
            "Spring",
            "Summer",
            "Fall",
            "Winter"
          ],
          "requireHeart": 0,
          "stackMin": 1,
          "stackMax": 1
        },
        {
          "item": "243",
          "quality": 0,
          "seasons": [
            "Spring",
            "Summer",
            "Fall",
            "Winter"
          ],
          "requireHeart": 0,
          "stackMin": 1,
          "stackMax": 1
        },
        {
          "item": "197",
          "quality": 0,
          "seasons": [
            "Spring",
            "Summer",
            "Fall",
            "Winter"
          ],
          "requireHeart": 0,
          "stackMin": 1,
          "stackMax": 1
        }
      ]
    },
    {
      "npc": "Example",
      "gifts": [
        {
          "item": "349",
          "quality": 0,
          "seasons": [
            "Spring",
            "Summer",
            "Fall",
            "Winter"
          ],
          "requireHeart": 0,
          "stackMin": 1,
          "stackMax": 1
        },
        {
          "item": "351",
          "quality": 0,
          "seasons": [
            "Spring",
            "Summer",
            "Fall",
            "Winter"
          ],
          "requireHeart": 0,
          "stackMin": 1,
          "stackMax": 1
        },
        {
          "item": "243",
          "quality": 0,
          "seasons": [
            "Spring",
            "Summer",
            "Fall",
            "Winter"
          ],
          "requireHeart": 0,
          "stackMin": 1,
          "stackMax": 1
        },
        {
          "item": "197",
          "quality": 0,
          "seasons": [
            "Spring",
            "Summer",
            "Fall",
            "Winter"
          ],
          "requireHeart": 0,
          "stackMin": 1,
          "stackMax": 1
        }
      ]
    },
    {
      "npc": "Evelyn",
      "gifts": [
        {
          "item": "223",
          "quality": 4,
          "seasons": [
            "Spring",
            "Summer",
            "Fall",
            "Winter"
          ],
          "requireHeart": 0,
          "stackMin": 1,
          "stackMax": 1
        },
        {
          "item": "220",
          "quality": 0,
          "seasons": [
            "Spring",
            "Summer",
            "Fall",
            "Winter"
          ],
          "requireHeart": 0,
          "stackMin": 1,
          "stackMax": 1
        },
        {
          "item": "201",
          "quality": 0,
          "seasons": [
            "Spring",
            "Summer",
            "Fall",
            "Winter"
          ],
          "requireHeart": 0,
          "stackMin": 1,
          "stackMax": 1
        },
        {
          "item": "205",
          "quality": 0,
          "seasons": [
            "Spring",
            "Summer",
            "Fall",
            "Winter"
          ],
          "requireHeart": 0,
          "stackMin": 1,
          "stackMax": 1
        }
      ]
    },
    {
      "npc": "George",
      "gifts": [
        {
          "item": "201",
          "quality": 0,
          "seasons": [
            "Spring",
            "Summer",
            "Fall",
            "Winter"
          ],
          "requireHeart": 0,
          "stackMin": 1,
          "stackMax": 1
        },
        {
          "item": "212",
          "quality": 0,
          "seasons": [
            "Spring",
            "Summer",
            "Fall",
            "Winter"
          ],
          "requireHeart": 0,
          "stackMin": 1,
          "stackMax": 1
        },
        {
          "item": "220",
          "quality": 0,
          "seasons": [
            "Spring",
            "Summer",
            "Fall",
            "Winter"
          ],
          "requireHeart": 0,
          "stackMin": 1,
          "stackMax": 1
        },
        {
          "item": "390",
          "quality": 0,
          "seasons": [
            "Spring",
            "Summer",
            "Fall",
            "Winter"
          ],
          "requireHeart": 0,
          "stackMin": 35,
          "stackMax": 35
        }
      ]
    },
    {
      "npc": "Gus",
      "gifts": [
        {
          "item": "241",
          "quality": 1,
          "seasons": [
            "Spring",
            "Summer",
            "Fall",
            "Winter"
          ],
          "requireHeart": 0,
          "stackMin": 1,
          "stackMax": 1
        },
        {
          "item": "196",
          "quality": 4,
          "seasons": [
            "Spring",
            "Summer",
            "Fall",
            "Winter"
          ],
          "requireHeart": 0,
          "stackMin": 1,
          "stackMax": 1
        },
        {
          "item": "199",
          "quality": 4,
          "seasons": [
            "Spring",
            "Summer",
            "Fall",
            "Winter"
          ],
          "requireHeart": 0,
          "stackMin": 1,
          "stackMax": 1
        },
        {
          "item": "649",
          "quality": 0,
          "seasons": [
            "Spring",
            "Summer",
            "Fall",
            "Winter"
          ],
          "requireHeart": 0,
          "stackMin": 1,
          "stackMax": 1
        }
      ]
    },
    {
      "npc": "Jas",
      "gifts": [
        {
          "item": "376",
          "quality": 4,
          "seasons": [
            "Spring",
            "Summer",
            "Fall",
            "Winter"
          ],
          "requireHeart": 0,
          "stackMin": 1,
          "stackMax": 1
        },
        {
          "item": "398",
          "quality": 0,
          "seasons": [
            "Spring",
            "Summer",
            "Fall",
            "Winter"
          ],
          "requireHeart": 0,
          "stackMin": 3,
          "stackMax": 3
        },
        {
          "item": "18",
          "quality": 4,
          "seasons": [
            "Spring",
            "Summer",
            "Fall",
            "Winter"
          ],
          "requireHeart": 0,
          "stackMin": 3,
          "stackMax": 4
        },
        {
          "item": "402",
          "quality": 4,
          "seasons": [
            "Spring",
            "Summer",
            "Fall",
            "Winter"
          ],
          "requireHeart": 0,
          "stackMin": 2,
          "stackMax": 3
        },
        {
          "item": "408",
          "quality": 0,
          "seasons": [
            "Spring",
            "Summer",
            "Fall",
            "Winter"
          ],
          "requireHeart": 0,
          "stackMin": 2,
          "stackMax": 3
        },
        {
          "item": "148",
          "quality": 4,
          "seasons": [
            "Spring",
            "Summer",
            "Fall",
            "Winter"
          ],
          "requireHeart": 0,
          "stackMin": 2,
          "stackMax": 3
        }
      ]
    },
    {
      "npc": "Jodi",
      "gifts": [
        {
          "item": "221",
          "quality": 0,
          "seasons": [
            "Spring",
            "Summer",
            "Fall",
            "Winter"
          ],
          "requireHeart": 0,
          "stackMin": 1,
          "stackMax": 1
        },
        {
          "item": "206",
          "quality": 0,
          "seasons": [
            "Spring",
            "Summer",
            "Fall",
            "Winter"
          ],
          "requireHeart": 0,
          "stackMin": 1,
          "stackMax": 1
        },
        {
          "item": "607",
          "quality": 0,
          "seasons": [
            "Spring",
            "Summer",
            "Fall",
            "Winter"
          ],
          "requireHeart": 0,
          "stackMin": 1,
          "stackMax": 1
        },
        {
          "item": "213",
          "quality": 0,
          "seasons": [
            "Spring",
            "Summer",
            "Fall",
            "Winter"
          ],
          "requireHeart": 0,
          "stackMin": 1,
          "stackMax": 1
        }
      ]
    },
    {
      "npc": "Kent",
      "gifts": [
        {
          "item": "214",
          "quality": 4,
          "seasons": [
            "Spring",
            "Summer",
            "Fall",
            "Winter"
          ],
          "requireHeart": 0,
          "stackMin": 1,
          "stackMax": 1
        },
        {
          "item": "562",
          "quality": 0,
          "seasons": [
            "Spring",
            "Summer",
            "Fall",
            "Winter"
          ],
          "requireHeart": 0,
          "stackMin": 1,
          "stackMax": 1
        },
        {
          "item": "903",
          "quality": 0,
          "seasons": [
            "Spring",
            "Summer",
            "Fall",
            "Winter"
          ],
          "requireHeart": 0,
          "stackMin": 1,
          "stackMax": 1
        },
        {
          "item": "288",
          "quality": 0,
          "seasons": [
            "Spring",
            "Summer",
            "Fall",
            "Winter"
          ],
          "requireHeart": 0,
          "stackMin": 4,
          "stackMax": 4
        }
      ]
    },
    {
      "npc": "Krobus",
      "gifts": [
        {
          "item": "769",
          "quality": 0,
          "seasons": [
            "Spring",
            "Summer",
            "Fall",
            "Winter"
          ],
          "requireHeart": 0,
          "stackMin": 4,
          "stackMax": 4
        },
        {
          "item": "796",
          "quality": 4,
          "seasons": [
            "Spring",
            "Summer",
            "Fall",
            "Winter"
          ],
          "requireHeart": 0,
          "stackMin": 1,
          "stackMax": 1
        },
        {
          "item": "157",
          "quality": 0,
          "seasons": [
            "Spring",
            "Summer",
            "Fall",
            "Winter"
          ],
          "requireHeart": 0,
          "stackMin": 4,
          "stackMax": 4
        },
        {
          "item": "153",
          "quality": 0,
          "seasons": [
            "Spring",
            "Summer",
            "Fall",
            "Winter"
          ],
          "requireHeart": 0,
          "stackMin": 8,
          "stackMax": 8
        }
      ]
    },
    {
      "npc": "Leo",
      "gifts": [
        {
          "item": "830",
          "quality": 4,
          "seasons": [
            "Spring",
            "Summer",
            "Fall",
            "Winter"
          ],
          "requireHeart": 0,
          "stackMin": 2,
          "stackMax": 2
        },
        {
          "item": "832",
          "quality": 0,
          "seasons": [
            "Spring",
            "Summer",
            "Fall",
            "Winter"
          ],
          "requireHeart": 0,
          "stackMin": 1,
          "stackMax": 1
        },
        {
          "item": "280",
          "quality": 4,
          "seasons": [
            "Spring",
            "Summer",
            "Fall",
            "Winter"
          ],
          "requireHeart": 8,
          "stackMin": 1,
          "stackMax": 1
        },
        {
          "item": "91",
          "quality": 0,
          "seasons": [
            "Spring",
            "Summer",
            "Fall",
            "Winter"
          ],
          "requireHeart": 0,
          "stackMin": 2,
          "stackMax": 2
        },
        {
          "item": "791",
          "quality": 0,
          "seasons": [
            "Spring",
            "Summer",
            "Fall",
            "Winter"
          ],
          "requireHeart": 0,
          "stackMin": 1,
          "stackMax": 1
        }
      ]
    },
    {
      "npc": "Lewis",
      "gifts": [
        {
          "item": "240",
          "quality": 1,
          "seasons": [
            "Spring",
            "Summer",
            "Fall",
            "Winter"
          ],
          "requireHeart": 0,
          "stackMin": 1,
          "stackMax": 1
        },
        {
          "item": "184",
          "quality": 4,
          "seasons": [
            "Spring",
            "Summer",
            "Fall",
            "Winter"
          ],
          "requireHeart": 0,
          "stackMin": 1,
          "stackMax": 1
        },
        {
          "item": "306",
          "quality": 2,
          "seasons": [
            "Spring",
            "Summer",
            "Fall",
            "Winter"
          ],
          "requireHeart": 0,
          "stackMin": 1,
          "stackMax": 1
        },
        {
          "item": "424",
          "quality": 1,
          "seasons": [
            "Spring",
            "Summer",
            "Fall",
            "Winter"
          ],
          "requireHeart": 0,
          "stackMin": 1,
          "stackMax": 1
        }
      ]
    },
    {
      "npc": "Linus",
      "gifts": [
        {
          "item": "422",
          "quality": 0,
          "seasons": [
            "Spring",
            "Summer",
            "Fall",
            "Winter"
          ],
          "requireHeart": 0,
          "stackMin": 1,
          "stackMax": 1
        },
        {
          "item": "635",
          "quality": 4,
          "seasons": [
            "Spring",
            "Summer",
            "Fall",
            "Winter"
          ],
          "requireHeart": 0,
          "stackMin": 1,
          "stackMax": 1
        },
        {
          "item": "16",
          "quality": 4,
          "seasons": [
            "Spring",
            "Summer",
            "Fall",
            "Winter"
          ],
          "requireHeart": 0,
          "stackMin": 2,
          "stackMax": 2
        },
        {
          "item": "20",
          "quality": 4,
          "seasons": [
            "Spring",
            "Summer",
            "Fall",
            "Winter"
          ],
          "requireHeart": 0,
          "stackMin": 2,
          "stackMax": 2
        },
        {
          "item": "396",
          "quality": 2,
          "seasons": [
            "Spring",
            "Summer",
            "Fall",
            "Winter"
          ],
          "requireHeart": 0,
          "stackMin": 2,
          "stackMax": 2
        },
        {
          "item": "259",
          "quality": 2,
          "seasons": [
            "Spring",
            "Summer",
            "Fall",
            "Winter"
          ],
          "requireHeart": 0,
          "stackMin": 2,
          "stackMax": 2
        },
        {
          "item": "406",
          "quality": 2,
          "seasons": [
            "Spring",
            "Summer",
            "Fall",
            "Winter"
          ],
          "requireHeart": 0,
          "stackMin": 2,
          "stackMax": 2
        },
        {
          "item": "412",
          "quality": 2,
          "seasons": [
            "Spring",
            "Summer",
            "Fall",
            "Winter"
          ],
          "requireHeart": 0,
          "stackMin": 2,
          "stackMax": 2
        },
        {
          "item": "416",
          "quality": 0,
          "seasons": [
            "Spring",
            "Summer",
            "Fall",
            "Winter"
          ],
          "requireHeart": 0,
          "stackMin": 2,
          "stackMax": 2
        }
      ]
    },
    {
      "npc": "Marnie",
      "gifts": [
        {
          "item": "206",
          "quality": 0,
          "seasons": [
            "Spring",
            "Summer",
            "Fall",
            "Winter"
          ],
          "requireHeart": 0,
          "stackMin": 1,
          "stackMax": 1
        },
        {
          "item": "221",
          "quality": 0,
          "seasons": [
            "Spring",
            "Summer",
            "Fall",
            "Winter"
          ],
          "requireHeart": 0,
          "stackMin": 1,
          "stackMax": 1
        },
        {
          "item": "200",
          "quality": 4,
          "seasons": [
            "Spring",
            "Summer",
            "Fall",
            "Winter"
          ],
          "requireHeart": 0,
          "stackMin": 1,
          "stackMax": 1
        },
        {
          "item": "436",
          "quality": 0,
          "seasons": [
            "Spring",
            "Summer",
            "Fall",
            "Winter"
          ],
          "requireHeart": 0,
          "stackMin": 1,
          "stackMax": 1
        }
      ]
    },
    {
      "npc": "Pam",
      "gifts": [
        {
          "item": "213",
          "quality": 0,
          "seasons": [
            "Spring",
            "Summer",
            "Fall",
            "Winter"
          ],
          "requireHeart": 0,
          "stackMin": 1,
          "stackMax": 1
        },
        {
          "item": "729",
          "quality": 4,
          "seasons": [
            "Spring",
            "Summer",
            "Fall",
            "Winter"
          ],
          "requireHeart": 0,
          "stackMin": 1,
          "stackMax": 1
        },
        {
          "item": "651",
          "quality": 0,
          "seasons": [
            "Spring",
            "Summer",
            "Fall",
            "Winter"
          ],
          "requireHeart": 0,
          "stackMin": 1,
          "stackMax": 1
        },
        {
          "item": "164",
          "quality": 2,
          "seasons": [
            "Spring",
            "Summer",
            "Fall",
            "Winter"
          ],
          "requireHeart": 0,
          "stackMin": 1,
          "stackMax": 1
        }
      ]
    },
    {
      "npc": "Pierre",
      "gifts": [
        {
          "item": "472",
          "quality": 0,
          "seasons": [
            "Spring"
          ],
          "requireHeart": 0,
          "stackMin": 10,
          "stackMax": 10
        },
        {
          "item": "475",
          "quality": 0,
          "seasons": [
            "Spring"
          ],
          "requireHeart": 0,
          "stackMin": 5,
          "stackMax": 5
        },
        {
          "item": "484",
          "quality": 0,
          "seasons": [
            "Summer"
          ],
          "requireHeart": 0,
          "stackMin": 5,
          "stackMax": 5
        },
        {
          "item": "485",
          "quality": 0,
          "seasons": [
            "Summer"
          ],
          "requireHeart": 0,
          "stackMin": 3,
          "stackMax": 3
        },
        {
          "item": "491",
          "quality": 0,
          "seasons": [
            "Fall"
          ],
          "requireHeart": 0,
          "stackMin": 5,
          "stackMax": 5
        },
        {
          "item": "489",
          "quality": 0,
          "seasons": [
            "Fall"
          ],
          "requireHeart": 0,
          "stackMin": 10,
          "stackMax": 10
        },
        {
          "item": "246",
          "quality": 0,
          "seasons": [
            "Spring",
            "Summer",
            "Fall",
            "Winter"
          ],
          "requireHeart": 0,
          "stackMin": 4,
          "stackMax": 4
        },
        {
          "item": "247",
          "quality": 0,
          "seasons": [
            "Spring",
            "Summer",
            "Fall",
            "Winter"
          ],
          "requireHeart": 0,
          "stackMin": 2,
          "stackMax": 2
        },
        {
          "item": "419",
          "quality": 0,
          "seasons": [
            "Spring",
            "Summer",
            "Fall",
            "Winter"
          ],
          "requireHeart": 0,
          "stackMin": 2,
          "stackMax": 2
        },
        {
          "item": "423",
          "quality": 0,
          "seasons": [
            "Spring",
            "Summer",
            "Fall",
            "Winter"
          ],
          "requireHeart": 0,
          "stackMin": 2,
          "stackMax": 2
        },
        {
          "item": "245",
          "quality": 0,
          "seasons": [
            "Spring",
            "Summer",
            "Fall",
            "Winter"
          ],
          "requireHeart": 0,
          "stackMin": 2,
          "stackMax": 2
        }
      ]
    },
    {
      "npc": "Robin",
      "gifts": [
        {
          "item": "388",
          "quality": 0,
          "seasons": [
            "Spring",
            "Summer",
            "Fall",
            "Winter"
          ],
          "requireHeart": 0,
          "stackMin": 50,
          "stackMax": 50
        },
        {
          "item": "709",
          "quality": 0,
          "seasons": [
            "Spring",
            "Summer",
            "Fall",
            "Winter"
          ],
          "requireHeart": 0,
          "stackMin": 10,
          "stackMax": 10
        },
        {
          "item": "207",
          "quality": 4,
          "seasons": [
            "Spring",
            "Summer",
            "Fall",
            "Winter"
          ],
          "requireHeart": 0,
          "stackMin": 1,
          "stackMax": 1
        },
        {
          "item": "197",
          "quality": 0,
          "seasons": [
            "Spring",
            "Summer",
            "Fall",
            "Winter"
          ],
          "requireHeart": 0,
          "stackMin": 1,
          "stackMax": 1
        },
        {
          "item": "236",
          "quality": 0,
          "seasons": [
            "Spring",
            "Summer",
            "Fall",
            "Winter"
          ],
          "requireHeart": 0,
          "stackMin": 1,
          "stackMax": 1
        }
      ]
    },
    {
      "npc": "Sandy",
      "gifts": [
        {
          "item": "60",
          "quality": 0,
          "seasons": [
            "Spring",
            "Summer",
            "Fall",
            "Winter"
          ],
          "requireHeart": 0,
          "stackMin": 1,
          "stackMax": 1
        },
        {
          "item": "64",
          "quality": 0,
          "seasons": [
            "Spring",
            "Summer",
            "Fall",
            "Winter"
          ],
          "requireHeart": 0,
          "stackMin": 1,
          "stackMax": 1
        },
        {
          "item": "218",
          "quality": 0,
          "seasons": [
            "Spring",
            "Summer",
            "Fall",
            "Winter"
          ],
          "requireHeart": 0,
          "stackMin": 1,
          "stackMax": 1
        },
        {
          "item": "802",
          "quality": 0,
          "seasons": [
            "Spring",
            "Summer",
            "Fall",
            "Winter"
          ],
          "requireHeart": 0,
          "stackMin": 5,
          "stackMax": 5
        }
      ]
    },
    {
      "npc": "Vincent",
      "gifts": [
        {
          "item": "562",
          "quality": 0,
          "seasons": [
            "Spring",
            "Summer",
            "Fall",
            "Winter"
          ],
          "requireHeart": 0,
          "stackMin": 1,
          "stackMax": 1
        },
        {
          "item": "60",
          "quality": 0,
          "seasons": [
            "Spring",
            "Summer",
            "Fall",
            "Winter"
          ],
          "requireHeart": 0,
          "stackMin": 1,
          "stackMax": 1
        },
        {
          "item": "220",
          "quality": 0,
          "seasons": [
            "Spring",
            "Summer",
            "Fall",
            "Winter"
          ],
          "requireHeart": 0,
          "stackMin": 1,
          "stackMax": 1
        },
        {
          "item": "394",
          "quality": 0,
          "seasons": [
            "Spring",
            "Summer",
            "Fall",
            "Winter"
          ],
          "requireHeart": 0,
          "stackMin": 1,
          "stackMax": 1
        },
        {
          "item": "604",
          "quality": 0,
          "seasons": [
            "Spring",
            "Summer",
            "Fall",
            "Winter"
          ],
          "requireHeart": 0,
          "stackMin": 1,
          "stackMax": 1
        },
        {
          "item": "72",
          "quality": 0,
          "seasons": [
            "Spring",
            "Summer",
            "Fall",
            "Winter"
          ],
          "requireHeart": 1,
          "stackMin": 1,
          "stackMax": 1
        }
      ]
    },
    {
      "npc": "Willy",
      "gifts": [
        {
          "item": "715",
          "quality": 4,
          "seasons": [
            "Spring",
            "Summer",
            "Fall",
            "Winter"
          ],
          "requireHeart": 0,
          "stackMin": 1,
          "stackMax": 1
        },
        {
          "item": "732",
          "quality": 0,
          "seasons": [
            "Spring",
            "Summer",
            "Fall",
            "Winter"
          ],
          "requireHeart": 0,
          "stackMin": 1,
          "stackMax": 1
        },
        {
          "item": "219",
          "quality": 4,
          "seasons": [
            "Spring",
            "Summer",
            "Fall",
            "Winter"
          ],
          "requireHeart": 0,
          "stackMin": 1,
          "stackMax": 1
        },
        {
          "item": "710",
          "quality": 0,
          "seasons": [
            "Spring",
            "Summer",
            "Fall",
            "Winter"
          ],
          "requireHeart": 0,
          "stackMin": 1,
          "stackMax": 1
        },
        {
          "item": "727",
          "quality": 4,
          "seasons": [
            "Spring",
            "Summer",
            "Fall",
            "Winter"
          ],
          "requireHeart": 0,
          "stackMin": 1,
          "stackMax": 1
        }
      ]
    },
    {
      "npc": "Wizard",
      "gifts": [
        {
          "item": "66",
          "quality": 0,
          "seasons": [
            "Spring",
            "Summer",
            "Fall",
            "Winter"
          ],
          "requireHeart": 0,
          "stackMin": 2,
          "stackMax": 2
        },
        {
          "item": "593",
          "quality": 4,
          "seasons": [
            "Spring",
            "Summer",
            "Fall",
            "Winter"
          ],
          "requireHeart": 0,
          "stackMin": 1,
          "stackMax": 1
        },
        {
          "item": "773",
          "quality": 0,
          "seasons": [
            "Spring",
            "Summer",
            "Fall",
            "Winter"
          ],
          "requireHeart": 0,
          "stackMin": 1,
          "stackMax": 1
        },
        {
          "item": "879",
          "quality": 0,
          "seasons": [
            "Spring",
            "Summer",
            "Fall",
            "Winter"
          ],
          "requireHeart": 0,
          "stackMin": 1,
          "stackMax": 1
        }
      ]
    },
    {
      "npc": "Claire",
      "gifts": [
        {
          "item": "350",
          "quality": 4,
          "seasons": [
            "Spring",
            "Summer",
            "Fall",
            "Winter"
          ],
          "requireHeart": 0,
          "stackMin": 1,
          "stackMax": 1
        },
        {
          "item": "815",
          "quality": 0,
          "seasons": [
            "Spring",
            "Summer",
            "Fall",
            "Winter"
          ],
          "requireHeart": 0,
          "stackMin": 3,
          "stackMax": 3
        },
        {
          "item": "Glazed Butterfish",
          "quality": 0,
          "seasons": [
            "Spring",
            "Summer",
            "Fall",
            "Winter"
          ],
          "requireHeart": 0,
          "stackMin": 1,
          "stackMax": 1
        },
        {
          "item": "395",
          "quality": 0,
          "seasons": [
            "Spring",
            "Summer",
            "Fall",
            "Winter"
          ],
          "requireHeart": 0,
          "stackMin": 2,
          "stackMax": 2
        }
      ]
    },
    {
      "npc": "Lance",
      "gifts": [
        {
          "item": "Bonefish",
          "quality": 0,
          "seasons": [
            "Spring",
            "Summer",
            "Fall",
            "Winter"
          ],
          "requireHeart": 0,
          "stackMin": 1,
          "stackMax": 1
        },
        {
          "item": "244",
          "quality": 0,
          "seasons": [
            "Spring",
            "Summer",
            "Fall",
            "Winter"
          ],
          "requireHeart": 0,
          "stackMin": 1,
          "stackMax": 1
        },
        {
          "item": "773",
          "quality": 0,
          "seasons": [
            "Spring",
            "Summer",
            "Fall",
            "Winter"
          ],
          "requireHeart": 0,
          "stackMin": 1,
          "stackMax": 1
        },
        {
          "item": "Frog Legs",
          "quality": 0,
          "seasons": [
            "Spring",
            "Summer",
            "Fall",
            "Winter"
          ],
          "requireHeart": 0,
          "stackMin": 1,
          "stackMax": 1
        }
      ]
    },
    {
      "npc": "Olivia",
      "gifts": [
        {
          "item": "336",
          "quality": 0,
          "seasons": [
            "Spring",
            "Summer",
            "Fall",
            "Winter"
          ],
          "requireHeart": 0,
          "stackMin": 1,
          "stackMax": 1
        },
        {
          "item": "907",
          "quality": 0,
          "seasons": [
            "Spring",
            "Summer",
            "Fall",
            "Winter"
          ],
          "requireHeart": 0,
          "stackMin": 1,
          "stackMax": 1
        },
        {
          "item": "224",
          "quality": 4,
          "seasons": [
            "Spring",
            "Summer",
            "Fall",
            "Winter"
          ],
          "requireHeart": 0,
          "stackMin": 1,
          "stackMax": 1
        },
        {
          "item": "231",
          "quality": 0,
          "seasons": [
            "Spring",
            "Summer",
            "Fall",
            "Winter"
          ],
          "requireHeart": 0,
          "stackMin": 1,
          "stackMax": 1
        }
      ]
    },
    {
      "npc": "Sophia",
      "gifts": [
        {
          "item": "340",
          "quality": 0,
          "seasons": [
            "Spring",
            "Summer",
            "Fall",
            "Winter"
          ],
          "requireHeart": 0,
          "stackMin": 1,
          "stackMax": 1
        },
        {
          "item": "Butterfish",
          "quality": 0,
          "seasons": [
            "Spring",
            "Summer",
            "Fall",
            "Winter"
          ],
          "requireHeart": 0,
          "stackMin": 1,
          "stackMax": 1
        },
        {
          "item": "Big Bark Burger",
          "quality": 0,
          "seasons": [
            "Spring",
            "Summer",
            "Fall",
            "Winter"
          ],
          "requireHeart": 0,
          "stackMin": 1,
          "stackMax": 1
        },
        {
          "item": "348",
          "quality": 0,
          "seasons": [
            "Spring",
            "Summer",
            "Fall",
            "Winter"
          ],
          "requireHeart": 0,
          "stackMin": 1,
          "stackMax": 1
        }
      ]
    },
    {
      "npc": "Victor",
      "gifts": [
        {
          "item": "348",
          "quality": 0,
          "seasons": [
            "Spring",
            "Summer",
            "Fall",
            "Winter"
          ],
          "requireHeart": 0,
          "stackMin": 1,
          "stackMax": 1
        },
        {
          "item": "Puppyfish",
          "quality": 0,
          "seasons": [
            "Spring",
            "Summer",
            "Fall",
            "Winter"
          ],
          "requireHeart": 0,
          "stackMin": 1,
          "stackMax": 1
        },
        {
          "item": "220",
          "quality": 0,
          "seasons": [
            "Spring",
            "Summer",
            "Fall",
            "Winter"
          ],
          "requireHeart": 0,
          "stackMin": 1,
          "stackMax": 1
        },
        {
          "item": "392",
          "quality": 4,
          "seasons": [
            "Spring",
            "Summer",
            "Fall",
            "Winter"
          ],
          "requireHeart": 0,
          "stackMin": 1,
          "stackMax": 1
        }
      ]
    },
    {
      "npc": "Magnus",
      "gifts": [
        {
          "item": "349",
          "quality": 0,
          "seasons": [
            "Spring",
            "Summer",
            "Fall",
            "Winter"
          ],
          "requireHeart": 0,
          "stackMin": 1,
          "stackMax": 1
        },
        {
          "item": "351",
          "quality": 0,
          "seasons": [
            "Spring",
            "Summer",
            "Fall",
            "Winter"
          ],
          "requireHeart": 0,
          "stackMin": 1,
          "stackMax": 1
        },
        {
          "item": "243",
          "quality": 0,
          "seasons": [
            "Spring",
            "Summer",
            "Fall",
            "Winter"
          ],
          "requireHeart": 0,
          "stackMin": 1,
          "stackMax": 1
        },
        {
          "item": "197",
          "quality": 0,
          "seasons": [
            "Spring",
            "Summer",
            "Fall",
            "Winter"
          ],
          "requireHeart": 0,
          "stackMin": 1,
          "stackMax": 1
        }
      ]
    },
    {
      "npc": "Andy",
      "gifts": [
        {
          "item": "167",
          "quality": 0,
          "seasons": [
            "Spring",
            "Summer",
            "Fall",
            "Winter"
          ],
          "requireHeart": 0,
          "stackMin": 5,
          "stackMax": 5
        },
        {
          "item": "727",
          "quality": 4,
          "seasons": [
            "Spring",
            "Summer",
            "Fall",
            "Winter"
          ],
          "requireHeart": 0,
          "stackMin": 1,
          "stackMax": 1
        },
        {
          "item": "205",
          "quality": 0,
          "seasons": [
            "Spring",
            "Summer",
            "Fall",
            "Winter"
          ],
          "requireHeart": 0,
          "stackMin": 1,
          "stackMax": 1
        },
        {
          "item": "230",
          "quality": 0,
          "seasons": [
            "Spring",
            "Summer",
            "Fall",
            "Winter"
          ],
          "requireHeart": 0,
          "stackMin": 1,
          "stackMax": 1
        },
        {
          "item": "466",
          "quality": 0,
          "seasons": [
            "Spring",
            "Summer",
            "Fall",
            "Winter"
          ],
          "requireHeart": 0,
          "stackMin": 5,
          "stackMax": 5
        }
      ]
    },
    {
      "npc": "Apples",
      "gifts": [
        {
          "item": "276",
          "quality": 0,
          "seasons": [
            "Spring",
            "Summer",
            "Fall",
            "Winter"
          ],
          "requireHeart": 0,
          "stackMin": 1,
          "stackMax": 1
        },
        {
          "item": "634",
          "quality": 4,
          "seasons": [
            "Spring",
            "Summer",
            "Fall",
            "Winter"
          ],
          "requireHeart": 0,
          "stackMin": 2,
          "stackMax": 2
        },
        {
          "item": "638",
          "quality": 4,
          "seasons": [
            "Spring",
            "Summer",
            "Fall",
            "Winter"
          ],
          "requireHeart": 0,
          "stackMin": 1,
          "stackMax": 1
        },
        {
          "item": "636",
          "quality": 4,
          "seasons": [
            "Spring",
            "Summer",
            "Fall",
            "Winter"
          ],
          "requireHeart": 0,
          "stackMin": 1,
          "stackMax": 1
        },
        {
          "item": "637",
          "quality": 4,
          "seasons": [
            "Spring",
            "Summer",
            "Fall",
            "Winter"
          ],
          "requireHeart": 0,
          "stackMin": 1,
          "stackMax": 1
        },
        {
          "item": "635",
          "quality": 4,
          "seasons": [
            "Spring",
            "Summer",
            "Fall",
            "Winter"
          ],
          "requireHeart": 0,
          "stackMin": 1,
          "stackMax": 1
        }
      ]
    },
    {
      "npc": "Gunther",
      "gifts": [
        {
          "item": "649",
          "quality": 0,
          "seasons": [
            "Spring",
            "Summer",
            "Fall",
            "Winter"
          ],
          "requireHeart": 0,
          "stackMin": 1,
          "stackMax": 1
        },
        {
          "item": "200",
          "quality": 4,
          "seasons": [
            "Spring",
            "Summer",
            "Fall",
            "Winter"
          ],
          "requireHeart": 0,
          "stackMin": 1,
          "stackMax": 1
        },
        {
          "item": "459",
          "quality": 0,
          "seasons": [
            "Spring",
            "Summer",
            "Fall",
            "Winter"
          ],
          "requireHeart": 0,
          "stackMin": 1,
          "stackMax": 1
        },
        {
          "item": "Butterfish",
          "quality": 0,
          "seasons": [
            "Spring",
            "Summer",
            "Fall",
            "Winter"
          ],
          "requireHeart": 0,
          "stackMin": 1,
          "stackMax": 1
        }
      ]
    },
    {
      "npc": "Martin",
      "gifts": [
        {
          "item": "618",
          "quality": 0,
          "seasons": [
            "Spring",
            "Summer",
            "Fall",
            "Winter"
          ],
          "requireHeart": 0,
          "stackMin": 1,
          "stackMax": 1
        },
        {
          "item": "349",
          "quality": 0,
          "seasons": [
            "Spring",
            "Summer",
            "Fall",
            "Winter"
          ],
          "requireHeart": 0,
          "stackMin": 1,
          "stackMax": 1
        },
        {
          "item": "Glazed Butterfish",
          "quality": 0,
          "seasons": [
            "Spring",
            "Summer",
            "Fall",
            "Winter"
          ],
          "requireHeart": 0,
          "stackMin": 1,
          "stackMax": 1
        },
        {
          "item": "634",
          "quality": 4,
          "seasons": [
            "Spring",
            "Summer",
            "Fall",
            "Winter"
          ],
          "requireHeart": 0,
          "stackMin": 2,
          "stackMax": 2
        }
      ]
    },
    {
      "npc": "Marlon",
      "gifts": [
        {
          "item": "422",
          "quality": 0,
          "seasons": [
            "Spring",
            "Summer",
            "Fall",
            "Winter"
          ],
          "requireHeart": 0,
          "stackMin": 1,
          "stackMax": 1
        },
        {
          "item": "308",
          "quality": 0,
          "seasons": [
            "Spring",
            "Summer",
            "Fall",
            "Winter"
          ],
          "requireHeart": 0,
          "stackMin": 1,
          "stackMax": 1
        },
        {
          "item": "355",
          "quality": 0,
          "seasons": [
            "Spring",
            "Summer",
            "Fall",
            "Winter"
          ],
          "requireHeart": 0,
          "stackMin": 2,
          "stackMax": 2
        },
        {
          "item": "78",
          "quality": 4,
          "seasons": [
            "Spring",
            "Summer",
            "Fall",
            "Winter"
          ],
          "requireHeart": 0,
          "stackMin": 4,
          "stackMax": 4
        }
      ]
    },
    {
      "npc": "Morris",
      "gifts": [
        {
          "item": "167",
          "quality": 0,
          "seasons": [
            "Spring",
            "Summer",
            "Fall",
            "Winter"
          ],
          "requireHeart": 0,
          "stackMin": 5,
          "stackMax": 5
        },
        {
          "item": "459",
          "quality": 0,
          "seasons": [
            "Spring",
            "Summer",
            "Fall",
            "Winter"
          ],
          "requireHeart": 0,
          "stackMin": 1,
          "stackMax": 1
        },
        {
          "item": "303",
          "quality": 0,
          "seasons": [
            "Spring",
            "Summer",
            "Fall",
            "Winter"
          ],
          "requireHeart": 0,
          "stackMin": 1,
          "stackMax": 1
        },
        {
          "item": "240",
          "quality": 1,
          "seasons": [
            "Spring",
            "Summer",
            "Fall",
            "Winter"
          ],
          "requireHeart": 0,
          "stackMin": 1,
          "stackMax": 1
        },
        {
          "item": "430",
          "quality": 0,
          "seasons": [
            "Spring",
            "Summer",
            "Fall",
            "Winter"
          ],
          "requireHeart": 0,
          "stackMin": 1,
          "stackMax": 1
        }
      ]
    },
    {
      "npc": "Morgan",
      "gifts": [
        {
          "item": "Frog Legs",
          "quality": 0,
          "seasons": [
            "Spring",
            "Summer",
            "Fall",
            "Winter"
          ],
          "requireHeart": 0,
          "stackMin": 1,
          "stackMax": 1
        },
        {
          "item": "604",
          "quality": 0,
          "seasons": [
            "Spring",
            "Summer",
            "Fall",
            "Winter"
          ],
          "requireHeart": 0,
          "stackMin": 1,
          "stackMax": 1
        },
        {
          "item": "612",
          "quality": 2,
          "seasons": [
            "Spring",
            "Summer",
            "Fall",
            "Winter"
          ],
          "requireHeart": 0,
          "stackMin": 1,
          "stackMax": 1
        },
        {
          "item": "422",
          "quality": 0,
          "seasons": [
            "Spring",
            "Summer",
            "Fall",
            "Winter"
          ],
          "requireHeart": 0,
          "stackMin": 1,
          "stackMax": 1
        }
      ]
    },
    {
      "npc": "Scarlett",
      "gifts": [
        {
          "item": "595",
          "quality": 0,
          "seasons": [
            "Spring",
            "Summer",
            "Fall",
            "Winter"
          ],
          "requireHeart": 0,
          "stackMin": 1,
          "stackMax": 1
        },
        {
          "item": "577",
          "quality": 0,
          "seasons": [
            "Spring",
            "Summer",
            "Fall",
            "Winter"
          ],
          "requireHeart": 0,
          "stackMin": 1,
          "stackMax": 1
        },
        {
          "item": "Grampleton Orange Chicken",
          "quality": 0,
          "seasons": [
            "Spring",
            "Summer",
            "Fall",
            "Winter"
          ],
          "requireHeart": 0,
          "stackMin": 1,
          "stackMax": 1
        },
        {
          "item": "430",
          "quality": 0,
          "seasons": [
            "Spring",
            "Summer",
            "Fall",
            "Winter"
          ],
          "requireHeart": 0,
          "stackMin": 1,
          "stackMax": 1
        }
      ]
    },
    {
      "npc": "Susan",
      "gifts": [
        {
          "item": "240",
          "quality": 1,
          "seasons": [
            "Spring",
            "Summer",
            "Fall",
            "Winter"
          ],
          "requireHeart": 0,
          "stackMin": 1,
          "stackMax": 1
        },
        {
          "item": "200",
          "quality": 4,
          "seasons": [
            "Spring",
            "Summer",
            "Fall",
            "Winter"
          ],
          "requireHeart": 0,
          "stackMin": 1,
          "stackMax": 1
        },
        {
          "item": "224",
          "quality": 4,
          "seasons": [
            "Spring",
            "Summer",
            "Fall",
            "Winter"
          ],
          "requireHeart": 0,
          "stackMin": 1,
          "stackMax": 1
        },
        {
          "item": "270",
          "quality": 4,
          "seasons": [
            "Spring",
            "Summer",
            "Fall",
            "Winter"
          ],
          "requireHeart": 0,
          "stackMin": 2,
          "stackMax": 3
        }
      ]
    }
  ]
}