{
  "RustySword_Name": "Rostiges Schwert",
  "RustySword_Description": "Ein rostiges, stumpfes Schwert.",
  "SilverSaber_Name": "Silbersäbel",
  "SilverSaber_Description": "Mit Silber überzogen, um ein Rosten zu verhindern.",
  "DarkSword_Name": "Dunkles Schwert",
  "DarkSword_Description": "Leuchtet mit einer mysteriösen Energie.",
  "HolyBlade_Name": "Heilige Klinge",
  "HolyBlade_Description": "Sie zu führen erfüllt einen mit Hoffnung.",
  "GalaxySword_Name": "Galaxie-Schwert",
  "GalaxySword_Description": "Du hast noch nie etwas Vergleichbares gesehen.",
  "BoneSword_Name": "Knochenschwert",
  "BoneSword_Description": "Ein sehr leichter Teil eines geschärften Knochens.",
  "IronEdge_Name": "Eiserne Klinge",
  "IronEdge_Description": "Ein schweres Breitschwert.",
  "TemplarsBlade_Name": "Templer-Klinge",
  "TemplarsBlade_Description": "Gehörte einst einem ehrenhaften Ritter.",
  "ObsidianEdge_Name": "Obsidian-Schneide",
  "ObsidianEdge_Description": "Ist enorm scharf.",
  "LavaKatana_Name": "Lava-Katana",
  "LavaKatana_Description": "Eine mächtige Klinge, die in einem Becken aus kochender Lava geschmiedet wurde.",
  "Claymore_Name": "Flamberge",
  "Claymore_Description": "Ist wirklich schwer.",
  "SteelSmallsword_Name": "Stahl-Kurzschwert",
  "SteelSmallsword_Description": "Eine gewöhnliche Metallklinge.",
  "WoodenBlade_Name": "Holzklinge",
  "WoodenBlade_Description": "Für ein geschnitztes Stück Holz nicht schlecht.",
  "InsectHead_Name": "Insektenkopf",
  "InsectHead_Description": "Nicht gerade angenehm zu schwingen.",
  "NeptunesGlaive_Name": "Neptuns Gleve",
  "NeptunesGlaive_Description": "Ein Erbstück von jenseits der Edelsteinsee.",
  "ForestSword_Name": "Waldschwert",
  "ForestSword_Description": "Wurde durch Waldmagie mächtig gemacht.",
  "CarvingKnife_Name": "Schnitzmesser",
  "CarvingKnife_Description": "Eine kleine, leichte Klinge.",
  "IronDirk_Name": "Eiserner Langdolch",
  "IronDirk_Description": "Ein gewöhnlicher Dolch.",
  "BurglarsShank_Name": "Einbrecher-Stecher",
  "BurglarsShank_Description": "Die bevorzugte Waffe für die Geschickten und Leisen.",
  "ShadowDagger_Name": "Schattendolch",
  "ShadowDagger_Description": "Wenn du die Klinge ans Ohr hältst, hörst du den Schrei von 1.000 Seelen.",
  "ElfBlade_Name": "Elfenklinge",
  "ElfBlade_Description": "Nur die geschickten Hände einer Elfe könnten diese Waffe herstellen.",
  "CrystalDagger_Name": "Kristalldolch",
  "CrystalDagger_Description": "Die Klinge besteht aus gereinigtem Quarz.",
  "WindSpire_Name": "Windspitze",
  "WindSpire_Description": "Eine gewandte kleine Klinge.",
  "GalaxyDagger_Name": "Galaxie-Dolch",
  "GalaxyDagger_Description": "Du hast noch nie etwas Vergleichbares gesehen.",
  "WoodClub_Name": "Holzknüppel",
  "WoodClub_Description": "Ein solides Stück Holz, grob in eine Knüppelform geschnitzt.",
  "AlexsBat_Name": "Alex' Schläger",
  "AlexsBat_Description": "Der Schlagpunkt ist von Alex' berühmtem Grand Slam verbeult.",
  "LeadRod_Name": "Bleirute",
  "LeadRod_Description": "Ist unglaublich schwer.",
  "WoodMallet_Name": "Holzhammer",
  "WoodMallet_Description": "Der solide Kopf hält ganz schön was aus. Für einen Knüppel relativ leicht.",
  "TheSlammer_Name": "Der Knaller",
  "TheSlammer_Description": "Ein extrem schwerer Hammer, der Feinde fliegen lässt.",
  "GalaxyHammer_Name": "Galaxie-Hammer",
  "GalaxyHammer_Description": "Aus einem ultraleichten Material, das du noch nie zuvor gesehen hast.",
  "SamsOldGuitar_Name": "Fins alte Gitarre",
  "SamsOldGuitar_Description": "Hat schon bessere Tage gesehen.",
  "Femur_Name": "Oberschenkelknochen",
  "Femur_Description": "Ein alter, schwerer Knochen, der über die Jahrhunderte von Schmutzschichten überzogen wurde.",
  "Slingshot_Name": "Schleuder",
  "Slingshot_Description": "Benötigt Steine als Munition.",
  "MasterSlingshot_Name": "Meister-Schleuder",
  "MasterSlingshot_Description": "Benötigt Steine als Munition.",
  "GalaxySlingshot_Name": "Galaxie-Schleuder",
  "GalaxySlingshot_Description": "Sieht wirklich mächtig aus.",
  "ElliottsPencil_Name": "Elliotts Bleistift",
  "ElliottsPencil_Description": "Elliott benutzt ihn, um sein Buch zu schreiben. Er ist sehr spitz!",
  "MarusWrench_Name": "Marus Schraubenschlüssel",
  "MarusWrench_Description": "Ein großer, metallener Schraubenschlüssel. Er riecht wie Maru.",
  "HarveysMallet_Name": "Harveys Holzhammer",
  "HarveysMallet_Description": "Bringt Erinnerungen aus Harveys Klinik zurück.",
  "PennysFryer_Name": "Laphis Bratpfanne",
  "PennysFryer_Description": "Laphis Lieblingspfanne. Irgendein zähes Zeug klebt darin fest.",
  "LeahsWhittler_Name": "Monas Schnitzer",
  "LeahsWhittler_Description": "Monas Lieblingswerkzeug, um Treibholz umzuformen.",
  "AbbysPlanchette_Name": "Lunys Planchette",
  "AbbysPlanchette_Description": "Aus feinem Marmorholz gemacht.",
  "SebsLostMace_Name": "Sebs verlorener Streitkolben",
  "SebsLostMace_Description": "Eine von Sebastians mittelalterlichen Nachbildungen.",
  "HaleysIron_Name": "Haleys Eisen",
  "HaleysIron_Description": "Ist sengend heiß und riecht nach Haleys Haaren.",
  "PiratesSword_Name": "Piratenschwert",
  "PiratesSword_Description": "Sieht so aus, als hätte ein Pirat es einst besessen.",
  "Cutlass_Name": "Entermesser",
  "Cutlass_Description": "Eine geschickt hergestellte Klinge.",
  "WickedKris_Name": "Gemeiner Kris",
  "WickedKris_Description": "Die Klinge ist aus einer Iridiumlegierung gemacht.",
  "Kudgel_Name": "Totschläger",
  "Kudgel_Description": "Der beste Kumpel eines Schlägers.",
  "Scythe_Name": "Sense",
  "Scythe_Description": "Kann Gras zu Heu schneiden, wenn du ein Silo hast.",
  "YetiTooth_Name": "Yeti-Zahn",
  "YetiTooth_Description": "Fühlt sich eisig kalt an.",
  "Rapier_Name": "Rapier",
  "Rapier_Description": "Eine elegante Klinge.",
  "SteelFalchion_Name": "Stahl-Falchion",
  "SteelFalchion_Description": "Leicht und mächtig.",
  "BrokenTrident_Name": "Zerbrochener Dreizack",
  "BrokenTrident_Description": "Kommt aus der See, ist aber immer noch scharf.",
  "TemperedBroadsword_Name": "Temperiertes Korbschwert",
  "TemperedBroadsword_Description": "Sieht so aus, als könnte es allem widerstehen.",
  "GoldenScythe_Name": "Goldene Sense",
  "GoldenScythe_Description": "Es ist stärker als eine normale Sense.",
  "DwarfSword_Name": "Zwergenschwert",
  "DwarfSword_Description": "Es ist uralt, aber die Klinge stumpft nie ab.",
  "DwarfHammer_Name": "Zwergenhammer",
  "DwarfHammer_Description": "Er gibt ein sehr schwaches surrendes Geräusch von sich.",
  "DwarfDagger_Name": "Zwergendolch",
  "DwarfDagger_Description": "Es ist uralt, aber die Klinge stumpft nie ab.",
  "DragontoothCutlass_Name": "Drachenzahn-Machete",
  "DragontoothCutlass_Description": "Die Klinge wurde aus einem magischen Zahn geschmiedet.",
  "DragontoothClub_Name": "Drachenzahn-Keule",
  "DragontoothClub_Description": "Diese Keule wurde aus einem magischen Zahn gefertigt.",
  "DragontoothShiv_Name": "Drachenzahn-Messer",
  "DragontoothShiv_Description": "Die Klinge wurde aus einem magischen Zahn geschmiedet.",
  "OssifiedBlade_Name": "Ossifizierte Klinge",
  "OssifiedBlade_Description": "Eine große, scharfe, aus Knochen geformte Klinge.",
  "IridiumNeedle_Name": "Iridium-Nadel",
  "IridiumNeedle_Description": "Die Spitze ist unglaublich scharf, sogar bis auf die atomare Ebene.",
  "InfinityBlade_Name": "Unendliche Klinge",
  "InfinityBlade_Description": "Die wahre Form des Galaxie-Schwertes.",
  "InfinityGavel_Name": "Unendlicher Hammer",
  "InfinityGavel_Description": "Die wahre Form des Galaxie-Hammers.",
  "InfinityDagger_Name": "Unendlicher Dolch",
  "InfinityDagger_Description": "Die wahre Form des Galaxie-Dolches.",
  "Meowmere_Name": "Meowmere",
  "Meowmere_Description": "Eine ungewöhnliche Waffe aus einem weit entfernten Land..."
}