{
  "ambient_Mine_Abigail": "Sinta a minha espada!",
  "ambient_Mine_Abigail~1": "Amo explorar as minas!",
  "ambient_Mine_Abigail~2": "Estamos indo para as minas {0}?",
  "ambient_Mine_Abigail~3": "Que legal!",
  "ambient_Woods_Abigail": "Mistério...",
  "ambient_Mines_Harvey": "Não sou muito de lutar...",
  "fight_Abigail": "Sinta a minha espada!",
  "fight_Abigail~1": "Pra traz!",
  "fight_Abigail~2": "AHH!",
  "fight_Abigail~3": "Uaaaaa!",
  "fight_Abigail~4": "Já acabou Jessica?",
  "fight_Alex": "Eu cuido desse.",
  "fight_Alex~1": "Vem tranquilo!",
  "fight_Alex~2": "RECEBA NA CABEÇA!",
  "fight_Alex~3": "Toma essa.",
  "fight_Alex~4": "Ahhhh!",
  "fight_Elliott": "Deixe meu amigo em paz!^Deixe minha amiga em paz!",
  "fight_Elliott~1": "Pra trás!",
  "fight_Elliott~2": "En Garde!",
  "fight_Emily": "Eeek!",
  "fight_Emily~1": "Cuidado!",
  "fight_Emily~2": "Se abaixa!",
  "fight_Haley": "Ewwww..",
  "fight_Haley~1": "Ick!",
  "fight_Haley~2": "Nojento!",
  "Mines_Harvey": "Não sou muito de lutar",
  "fight_Harvey": "A seringa é a mais poderosa!",
  "fight_Harvey~1": "Poder vir!",
  "fight_Harvey~2": "Sorte que trouxe band-aid!",
  "fight_Harvey~3": "Hora de tomar remédios!",
  "fight_Leah": "Se prepare!",
  "fight_Leah~1": "{0}, time cuidado!",
  "fight_Leah~2": "Hyaaa!",
  "fight_Maru": "Yikes!",
  "fight_Maru~1": "Queria ter uma invenção aqui...",
  "fight_Maru~2": "Oh!",
  "fight_Penny": "Eeep!",
  "fight_Penny~1": "...!",
  "fight_Penny~2": "Sai de perto!",
  "fight_Sam": "Deixa comigo!.",
  "fight_Sam~1": "SANGUE DE YOBA TEM PODER!",
  "fight_Sam~2": "Volta aqui!",
  "fight_Sam~3": "É melhor correr!",
  "fight_Sebastian": "Bora lá!",
  "fight_Sebastian~1": "Toma essa!",
  "fight_Sebastian~2": "Falhar não é opção!",
  "fight_Sebastian~3": "Hyaaaa!",
  "fight_Shane": "Sai do meu rosto.",
  "fight_Shane~1": "Grrr!",
  "fight_Shane~2": "Vou acabar com você",
  "fight_Shane~3": "Sai de perto de mim."
}
